d_jwt_auth
